tunacell/__init__.py
tunacell/__main__.py
tunacell/base/__init__.py
tunacell/base/cell.py
tunacell/base/colony.py
tunacell/base/container.py
tunacell/base/datatools.py
tunacell/base/experiment.py
tunacell/base/lineage.py
tunacell/base/observable.py
tunacell/base/parser.py
tunacell/base/timeseries.py
tunacell/filters/__init__.py
tunacell/filters/cells.py
tunacell/filters/containers.py
tunacell/filters/lineages.py
tunacell/filters/main.py
tunacell/filters/trees.py
tunacell/io/__init__.py
tunacell/io/analysis.py
tunacell/io/metadata.py
tunacell/io/supersegger.py
tunacell/io/text.py
tunacell/plotting/__init__.py
tunacell/plotting/defs.py
tunacell/plotting/dynamics.py
tunacell/plotting/helpers.py
tunacell/plotting/samples.py
tunacell/plotting/statics.py
tunacell/plotting/timeseries.py
tunacell/simu/__init__.py
tunacell/simu/base.py
tunacell/simu/main.py
tunacell/simu/ou.py
tunacell/simu/run.py
tunacell/stats/__init__.py
tunacell/stats/api.py
tunacell/stats/compute.py
tunacell/stats/single.py
tunacell/stats/two.py
tunacell/stats/utils.py
tunacell/tests/__init__.py
tunacell/tests/test_cell_colony.py
tunacell/tests/test_container.py
tunacell/tests/test_experiment.py
tunacell/tests/test_filters.py
tunacell/tests/test_io_text.py
tunacell/tests/test_metadata.py
tunacell/tests/test_observable.py
tunacell/tests/test_simu.py
tunacell-0.2.2.dist-info/LICENSE
tunacell-0.2.2.dist-info/METADATA
tunacell-0.2.2.dist-info/WHEEL
tunacell-0.2.2.dist-info/entry_points.txt
tunacell-0.2.2.dist-info/top_level.txt
tunacell-0.2.2.dist-info/RECORD
