Metadata-Version: 2.1
Name: tunacell
Version: 0.2.2
Summary: Analysis of Timeseries from dividing UNicellular microorganisms
Home-page: https://github.com/LeBarbouze/tunacell
Author: Joachim Rambeau
Author-email: joachim.rambeau@gmail.com
License: MIT
Keywords: microscopy time-lapse bacteria cell-division analysis statistics dynamics cross-correlations
Platform: UNKNOWN
Classifier: Programming Language :: Python
Classifier: Programming Language :: Python :: 2.7
Classifier: Programming Language :: Python :: 3.6
Classifier: Programming Language :: Python :: 3.7
Classifier: Development Status :: 4 - Beta
Classifier: License :: OSI Approved :: MIT License
Classifier: Topic :: Scientific/Engineering :: Bio-Informatics
Requires-Dist: numpy
Requires-Dist: scipy
Requires-Dist: pandas
Requires-Dist: treelib
Requires-Dist: matplotlib (>=2)
Requires-Dist: future
Requires-Dist: dill
Requires-Dist: PyYAML
Requires-Dist: tqdm
Requires-Dist: tabulate
